config.py
search/__init__.py
search/bm25.py
search/indexer.py
search/vector.py
server.py
vault/__init__.py
vault/reader.py
vault_retriever-1.0.0.dist-info/METADATA
vault_retriever-1.0.0.dist-info/WHEEL
vault_retriever-1.0.0.dist-info/entry_points.txt
vault_retriever-1.0.0.dist-info/licenses/LICENSE
vault_retriever-1.0.0.dist-info/RECORD
