Metadata-Version: 2.4
Name: vault-retriever
Version: 1.0.0
Summary: Vault Retriever - Obsidian 知识库智能检索服务
Project-URL: Homepage, https://github.com/chyax98/vault-retriever
Project-URL: Repository, https://github.com/chyax98/vault-retriever
Author-email: chyax98 <chyax98@gmail.com>
License-Expression: MIT
License-File: LICENSE
Keywords: knowledge-base,mcp,obsidian,rag,retriever,semantic-search
Classifier: Development Status :: 4 - Beta
Classifier: Intended Audience :: Developers
Classifier: License :: OSI Approved :: MIT License
Classifier: Programming Language :: Python :: 3.12
Classifier: Programming Language :: Python :: 3.13
Classifier: Topic :: Text Processing :: Indexing
Requires-Python: >=3.12
Requires-Dist: bm25s>=0.2.14
Requires-Dist: fastembed>=0.7.4
Requires-Dist: fastmcp>=2.14.1
Requires-Dist: jieba>=0.42.1
Requires-Dist: lancedb>=0.26.0
Requires-Dist: networkx>=3.6.1
Requires-Dist: psutil>=7.2.0
Requires-Dist: scipy>=1.16.3
Provides-Extra: dev
Requires-Dist: pytest>=8.0.0; extra == 'dev'
